[
  {
    "CategroyId": "1",
    "Category": "Maths by Standard",
    "Courses": [
      {
        "CourseId": "1.1",
        "Name": "5th std",
        "Link": "/in-fifth-grade-math"
      },
      {
        "CourseId": "1.2",
        "Name": "6th std",
        "Link": "/in-in-class-6th-math-cbse"
      },
      {
        "CourseId": "1.3",
        "Name": "7th std",
        "Link": "/in-in-class-7th-math-cbse"
      },
      {
        "CourseId": "1.4",
        "Name": "8th std",
        "Link": "/in-in-class-8th-math-cbse"
      },
      {
        "CourseId": "1.5",
        "Name": "9th std",
        "Link": "/in-in-grade-9-ncert"
      },
      {
        "CourseId": "1.6",
        "Name": "10th std",
        "Link": "/in-in-grade-10-ncert"
      },
      {
        "CourseId": "1.7",
        "Name": "11th std",
        "Link": "/in-in-grade-11-ncert"
      },
      {
        "CourseId": "1.8",
        "Name": "12th std",
        "Link": "/in-in-grade-12-ncert"
      }
    ]
  },
  {
    "CategoryId": 2,
    "Category": "Maths in Hindi",
    "Courses": [
      {
        "CourseId": "2.1",
        "Name": "7th std",
        "Link": "/in-in-class-7th-math-cbse-hindi"
      },
      {
        "CourseId": "2.2",
        "Name": "8th std",
        "Link": "/in-in-class-8-math-india-hindi"
      },
      {
        "CourseId": "2.3",
        "Name": "9th std",
        "Link": "/in-in-class-9-math-india-hindi"
      },
      {
        "CourseId": "2.4",
        "Name": "10th std",
        "Link": "/in-in-class-10-math-cbse-hindi"
      },
      {
        "CourseId": "2.5",
        "Name": "11th std",
        "Link": "/in-in-class-11-math-cbse-hindi"
      }
    ]
  },
  {
    "CategoryId": "3",
    "Category": "Conceptual Maths",
    "Courses": [
      {
        "CourseId": "3.1",
        "Name": "Early Maths",
        "Link": "/early-math"
      },
      {
        "CourseId": "3.2",
        "Name": "Arithmetic",
        "Link": "/arithmetic"
      },
      {
        "CourseId": "3.3",
        "Name": "Pre-Algebra",
        "Link": "/pre-algebra"
      },
      {
        "CourseId": "3.4",
        "Name": "Algebra",
        "Link": "/algebra"
      },
      {
        "CourseId": "3.5",
        "Name": "Geometry",
        "Link": "/geometry-home"
      },
      {
        "CourseId": "3.6",
        "Name": "Algebra 2",
        "Link": "/algebra2"
      },
      {
        "CourseId": "3.7",
        "Name": "Trigonometry",
        "Link": "/trigonometry"
      },
      {
        "CourseId": "3.8",
        "Name": "Statistics-Probability",
        "Link": "/statistics-probability"
      },
      {
        "CourseId": "3.9",
        "Name": "Linear Algebra",
        "Link": "/linear-algebra"
      },
      {
        "CourseId": "3.10",
        "Name": "Math for Fun and Glory",
        "Link": "/math-for-fun-and-glory"
      }
    ]
  },
  {
    "CategoryId": "4",
    "Category": "Science for everyone",
    "Courses": [
      {
        "CourseId": "4.1",
        "Name": "Physics",
        "Link": "/physics"
      },
      {
        "CourseId": "4.2",
        "Name": "Chemistry",
        "Link": "/chemistry"
      },
      {
        "CourseId": "4.3",
        "Name": "Biology",
        "Link": "/biology"
      }
    ]
  },
  {
    "CategoryId": "5",
    "Category": "English Grammar",
    "Courses": [
      {
        "CourseId": "5.1",
        "Name": "Grammar",
        "Link": "/grammar"
      }  
    ]
  }
]
